[
    {
        "id": "17934540163096733",
        "created_at": 1527612091,
        "text": "\u043c\u0430\u0440\u043a\u0435\u0442\u0438\u043d\u0433 180 \u043b\u0432\u043b )))",
        "owner": {
            "id": "7176598810",
            "is_verified": false,
            "profile_pic_url": "https://instagram.fsdv1-2.fna.fbcdn.net/v/t51.2885-19/464760996_1254146839119862_3605321457742435801_n.png?stp=dst-jpg_s150x150_tt6&efg=eyJ2ZW5jb2RlX3RhZyI6InByb2ZpbGVfcGljLmRqYW5nby4xNTAuYzIifQ&_nc_ht=instagram.fsdv1-2.fna.fbcdn.net&_nc_cat=1&_nc_oc=Q6cZ2QHfvPinENG-UXbxkhKg5XuO4DjJAZPQQWuZ8CjvM95MNjDNZz5fOEoENHubUrlc7mk&_nc_ohc=YWvglMI4f-cQ7kNvwFAT5Qz&_nc_gid=tQdSKa33rVmLjaXNzJWzRQ&edm=ANTKIIoBAAAA&ccb=7-5&ig_cache_key=YW5vbnltb3VzX3Byb2ZpbGVfcGlj.3-ccb7-5&oh=00_AfZNsrU_PFLvCN2C-s_sMjuMvhVq4JfwqEKL5uvOJaz19A&oe=68E0C728&_nc_sid=d885a2",
            "username": "tonnykubinka"
        },
        "likes_count": 0,
        "answers": []
    },
    {
        "id": "17861800735140216",
        "created_at": 1497474668,
        "text": "\u00ab\u044f \u0432\u0430\u043c \u043f\u043e\u043a\u0430\u0436\u0443 \u043a\u0443\u0437\u044c\u043a\u0438\u043d\u0443 \u043c\u0430\u0442\u044c\u00bb \ud83d\ude0a",
        "owner": {
            "id": "4758795976",
            "is_verified": false,
            "profile_pic_url": "https://instagram.fsdv1-2.fna.fbcdn.net/v/t51.2885-19/17334221_1819077508341642_3765744101551505408_n.jpg?stp=dst-jpg_s150x150_tt6&efg=eyJ2ZW5jb2RlX3RhZyI6InByb2ZpbGVfcGljLmRqYW5nby42MDAuYzIifQ&_nc_ht=instagram.fsdv1-2.fna.fbcdn.net&_nc_cat=106&_nc_oc=Q6cZ2QHfvPinENG-UXbxkhKg5XuO4DjJAZPQQWuZ8CjvM95MNjDNZz5fOEoENHubUrlc7mk&_nc_ohc=8etblNVw2m0Q7kNvwHR5qrq&_nc_gid=tQdSKa33rVmLjaXNzJWzRQ&edm=ANTKIIoBAAAA&ccb=7-5&oh=00_AfZSvC5fZZE4kiazZsgl4IC-fT2ftny27PHzq6Jz5tKsNw&oe=68E09822&_nc_sid=d885a2",
            "username": "varelanesabaka"
        },
        "likes_count": 0,
        "answers": []
    },
    {
        "id": "17863773613095636",
        "created_at": 1491717822,
        "text": "\u0411\u044b\u043b\u0438 \u0432\u0440\u0435\u043c\u0435\u043d\u0430...",
        "owner": {
            "id": "3943239199",
            "is_verified": false,
            "profile_pic_url": "https://instagram.ftlv18-1.fna.fbcdn.net/v/t51.2885-19/30948606_183862295763047_5022436701839032320_n.jpg?stp=dst-jpg_s150x150_tt6&efg=eyJ2ZW5jb2RlX3RhZyI6InByb2ZpbGVfcGljLmRqYW5nby41NDUuYzIifQ&_nc_ht=instagram.ftlv18-1.fna.fbcdn.net&_nc_cat=111&_nc_oc=Q6cZ2QHfvPinENG-UXbxkhKg5XuO4DjJAZPQQWuZ8CjvM95MNjDNZz5fOEoENHubUrlc7mk&_nc_ohc=tLTjXV81RvQQ7kNvwHU0HqY&_nc_gid=tQdSKa33rVmLjaXNzJWzRQ&edm=ANTKIIoBAAAA&ccb=7-5&oh=00_AfaB_JrVHW22bJaAHbblLp5dCxRSlgOUPKBNzp6A1RCY1A&oe=68E091BF&_nc_sid=d885a2",
            "username": "svokna_"
        },
        "likes_count": 0,
        "answers": []
    },
    {
        "id": "17862461002097852",
        "created_at": 1488098258,
        "text": "\u0416\u0430\u043b\u044c \u0437\u0430\u043a\u0440\u0430\u0441\u0438\u043b\u0438!!!(",
        "owner": {
            "id": "2225367326",
            "is_verified": false,
            "profile_pic_url": "https://instagram.ftlv27-1.fna.fbcdn.net/v/t51.2885-19/42002785_1111987252286140_4138810046123343872_n.jpg?stp=dst-jpg_s150x150_tt6&efg=eyJ2ZW5jb2RlX3RhZyI6InByb2ZpbGVfcGljLmRqYW5nby4yNzAuYzIifQ&_nc_ht=instagram.ftlv27-1.fna.fbcdn.net&_nc_cat=104&_nc_oc=Q6cZ2QHfvPinENG-UXbxkhKg5XuO4DjJAZPQQWuZ8CjvM95MNjDNZz5fOEoENHubUrlc7mk&_nc_ohc=6UdLKPiSyskQ7kNvwGx_jkb&_nc_gid=tQdSKa33rVmLjaXNzJWzRQ&edm=ANTKIIoBAAAA&ccb=7-5&oh=00_AfYrI76jHth5mwgqeo6DTklgm7ul2XFNFzvhdaRFar3-Bw&oe=68E09A6D&_nc_sid=d885a2",
            "username": "ghostmj11"
        },
        "likes_count": 1,
        "answers": []
    },
    {
        "id": "17862739366074662",
        "created_at": 1485661013,
        "text": "\u0412\u0435\u043b\u0438\u043a\u043e\u043b\u0435\u043f\u043d\u043e!",
        "owner": {
            "id": "1978546309",
            "is_verified": false,
            "profile_pic_url": "https://instagram.ftlv18-1.fna.fbcdn.net/v/t51.2885-19/205290403_521167685694610_5383152812649746333_n.jpg?stp=dst-jpg_s150x150_tt6&efg=eyJ2ZW5jb2RlX3RhZyI6InByb2ZpbGVfcGljLmRqYW5nby4zODYuYzIifQ&_nc_ht=instagram.ftlv18-1.fna.fbcdn.net&_nc_cat=110&_nc_oc=Q6cZ2QHfvPinENG-UXbxkhKg5XuO4DjJAZPQQWuZ8CjvM95MNjDNZz5fOEoENHubUrlc7mk&_nc_ohc=B35PZqtZ5AsQ7kNvwEIB5Dm&_nc_gid=tQdSKa33rVmLjaXNzJWzRQ&edm=ANTKIIoBAAAA&ccb=7-5&oh=00_AfYk3pzDwwOoxG_k2w3_WYt567VpRoSUbWJOMOZTOSG53Q&oe=68E0AD77&_nc_sid=d885a2",
            "username": "danexshop"
        },
        "likes_count": 0,
        "answers": []
    },
    {
        "id": "17871077596050558",
        "created_at": 1484928133,
        "text": "@konstantin.nomer1 \u043a\u0430\u043d\u0435\u0448",
        "owner": {
            "id": "1921708512",
            "is_verified": false,
            "profile_pic_url": "https://instagram.ftlv27-1.fna.fbcdn.net/v/t51.2885-19/59335079_2025085557600952_997056982521217024_n.jpg?stp=dst-jpg_s150x150_tt6&efg=eyJ2ZW5jb2RlX3RhZyI6InByb2ZpbGVfcGljLmRqYW5nby4xMDgwLmMyIn0&_nc_ht=instagram.ftlv27-1.fna.fbcdn.net&_nc_cat=104&_nc_oc=Q6cZ2QHfvPinENG-UXbxkhKg5XuO4DjJAZPQQWuZ8CjvM95MNjDNZz5fOEoENHubUrlc7mk&_nc_ohc=xfIuUQdy_74Q7kNvwEaVkaF&_nc_gid=tQdSKa33rVmLjaXNzJWzRQ&edm=ANTKIIoBAAAA&ccb=7-5&oh=00_AfanZorbQ_cuKLcU3cANY2sWvbOeThFE3I7PhM9TMlqh6Q&oe=68E0BBB3&_nc_sid=d885a2",
            "username": "zoomstreetart"
        },
        "likes_count": 1,
        "answers": []
    },
    {
        "id": "17847343000186301",
        "created_at": 1484853496,
        "text": "@zoomstreetart \u0434\u0430 \u0445\u043e\u0442\u0435\u043b \u0441\u0444\u043e\u0442\u043a\u0430\u0442\u044c, \u043d\u043e \u043a\u0430\u043a-\u0442\u043e \u043e\u0444\u0438\u0433\u0435\u043b, \u0448\u0435\u043b \u0434\u043e\u0432\u043e\u043b\u044c\u043d\u044b\u0439 \u0441\u0444\u043e\u0442\u043a\u0430\u0442\u044c,  \u043d\u0435 \u0443\u0441\u043f\u0435\u043b \u043f\u043e\u0434\u043e\u0439\u0442\u0438, \u0430 \u043e\u043d\u0438 \u0437\u0430\u043a\u0440\u0430\u0441\u0438\u043b\u0438 \u0435\u0435 \u0437\u0430 10 \u0441\u0435\u043a\u0443\u043d\u0434, \u0442\u0430\u043a \u043e\u0431\u0438\u0434\u043d\u043e (( \u043c\u043e\u0436\u043d\u043e \u0442\u0432\u043e\u044e \u0432\u044b\u043b\u043e\u0436\u0443 \u043a \u0441\u0435\u0431\u0435?",
        "owner": {
            "id": "305059483",
            "is_verified": false,
            "profile_pic_url": "https://instagram.fsdv1-2.fna.fbcdn.net/v/t51.2885-19/328841832_915107739663338_6727700082555893020_n.jpg?stp=dst-jpg_s150x150_tt6&efg=eyJ2ZW5jb2RlX3RhZyI6InByb2ZpbGVfcGljLmRqYW5nby4xMDgwLmMyIn0&_nc_ht=instagram.fsdv1-2.fna.fbcdn.net&_nc_cat=102&_nc_oc=Q6cZ2QHfvPinENG-UXbxkhKg5XuO4DjJAZPQQWuZ8CjvM95MNjDNZz5fOEoENHubUrlc7mk&_nc_ohc=20G2wemlwhoQ7kNvwEX-HGa&_nc_gid=tQdSKa33rVmLjaXNzJWzRQ&edm=ANTKIIoBAAAA&ccb=7-5&oh=00_Afa0qWHZPbiZBFolcU73JKOkZEcRpxJoTGNFQmhWENL4AA&oe=68E09135&_nc_sid=d885a2",
            "username": "konstantin.nomer1"
        },
        "likes_count": 1,
        "answers": []
    },
    {
        "id": "17858572531125507",
        "created_at": 1484844336,
        "text": "\u0445\u0440\u0443\u0449\u0435\u0432 \u0437\u0430 \u043a\u0430\u0441\u0441\u043e\u0439))) \u043d\u0438\u0447\u0435\u0433\u043e \u043d\u0435 \u043f\u043e\u043c\u0435\u043d\u044f\u043b\u043e\u0441\u044c! \u043c\u0443\u043c\u0438\u044f \u0445\u0440\u0443\u0449\u0430 \u043f\u0440\u043e\u0434\u0430\u0441\u0442 \u0432\u0430\u043c \u043e\u0434\u0438\u043d \u043a\u0440\u043e\u0441\u0441\u043e\u0432\u043e\u043a",
        "owner": {
            "id": "240162164",
            "is_verified": false,
            "profile_pic_url": "https://instagram.ftlv18-1.fna.fbcdn.net/v/t51.2885-19/11348230_1609229466010977_1221587787_a.jpg?stp=dst-jpg_s150x150_tt6&efg=eyJ2ZW5jb2RlX3RhZyI6InByb2ZpbGVfcGljLmRqYW5nby4xNTAuYzIifQ&_nc_ht=instagram.ftlv18-1.fna.fbcdn.net&_nc_cat=109&_nc_oc=Q6cZ2QHfvPinENG-UXbxkhKg5XuO4DjJAZPQQWuZ8CjvM95MNjDNZz5fOEoENHubUrlc7mk&_nc_ohc=VzOpWO9oGmwQ7kNvwGsa90u&_nc_gid=tQdSKa33rVmLjaXNzJWzRQ&edm=ANTKIIoBAAAA&ccb=7-5&oh=00_AfbG5vYFs9uX0nrawCuVLqfczkOGG847KT9XvJmA6ECHlA&oe=68E09D1A&_nc_sid=d885a2",
            "username": "jetset13"
        },
        "likes_count": 0,
        "answers": []
    },
    {
        "id": "17859196702097839",
        "created_at": 1484838230,
        "text": "@konstantin.nomer1 \u0441\u0444\u043e\u0442\u043a\u0430\u043b \u0431\u044b \u043f\u0440\u043e\u0446\u0435\u0441\u0441, \u044d\u0442\u043e \u0438\u043d\u0442\u0435\u0440\u0435\u0441\u043d\u043e",
        "owner": {
            "id": "1921708512",
            "is_verified": false,
            "profile_pic_url": "https://instagram.ftlv27-1.fna.fbcdn.net/v/t51.2885-19/59335079_2025085557600952_997056982521217024_n.jpg?stp=dst-jpg_s150x150_tt6&efg=eyJ2ZW5jb2RlX3RhZyI6InByb2ZpbGVfcGljLmRqYW5nby4xMDgwLmMyIn0&_nc_ht=instagram.ftlv27-1.fna.fbcdn.net&_nc_cat=104&_nc_oc=Q6cZ2QHfvPinENG-UXbxkhKg5XuO4DjJAZPQQWuZ8CjvM95MNjDNZz5fOEoENHubUrlc7mk&_nc_ohc=xfIuUQdy_74Q7kNvwEaVkaF&_nc_gid=tQdSKa33rVmLjaXNzJWzRQ&edm=ANTKIIoBAAAA&ccb=7-5&oh=00_AfanZorbQ_cuKLcU3cANY2sWvbOeThFE3I7PhM9TMlqh6Q&oe=68E0BBB3&_nc_sid=d885a2",
            "username": "zoomstreetart"
        },
        "likes_count": 0,
        "answers": []
    },
    {
        "id": "17869795855046784",
        "created_at": 1484830965,
        "text": "\u0422\u043e\u043b\u044c\u043a\u043e \u0447\u0442\u043e \u0437\u0430\u043a\u0440\u0430\u0441\u0438\u043b\u0438,  \u043d\u0435 \u0443\u0441\u043f\u0435\u043b 30 \u0441\u0435\u043a\u0443\u043d\u0434 \u0434\u043e\u0431\u0435\u0436\u0430\u0442\u044c (( \u0443\u0432\u044b\u2026",
        "owner": {
            "id": "305059483",
            "is_verified": false,
            "profile_pic_url": "https://instagram.fsdv1-2.fna.fbcdn.net/v/t51.2885-19/328841832_915107739663338_6727700082555893020_n.jpg?stp=dst-jpg_s150x150_tt6&efg=eyJ2ZW5jb2RlX3RhZyI6InByb2ZpbGVfcGljLmRqYW5nby4xMDgwLmMyIn0&_nc_ht=instagram.fsdv1-2.fna.fbcdn.net&_nc_cat=102&_nc_oc=Q6cZ2QHfvPinENG-UXbxkhKg5XuO4DjJAZPQQWuZ8CjvM95MNjDNZz5fOEoENHubUrlc7mk&_nc_ohc=20G2wemlwhoQ7kNvwEX-HGa&_nc_gid=tQdSKa33rVmLjaXNzJWzRQ&edm=ANTKIIoBAAAA&ccb=7-5&oh=00_Afa0qWHZPbiZBFolcU73JKOkZEcRpxJoTGNFQmhWENL4AA&oe=68E09135&_nc_sid=d885a2",
            "username": "konstantin.nomer1"
        },
        "likes_count": 1,
        "answers": []
    },
    {
        "id": "17848814422142786",
        "created_at": 1484825169,
        "text": "\u041b\u0430\u0436\u0430",
        "owner": {
            "id": "42749573",
            "is_verified": false,
            "profile_pic_url": "https://instagram.ftlv18-1.fna.fbcdn.net/v/t51.2885-19/11358094_958469344176046_2069539223_a.jpg?stp=dst-jpg_s150x150_tt6&efg=eyJ2ZW5jb2RlX3RhZyI6InByb2ZpbGVfcGljLmRqYW5nby4xNTAuYzIifQ&_nc_ht=instagram.ftlv18-1.fna.fbcdn.net&_nc_cat=110&_nc_oc=Q6cZ2QHfvPinENG-UXbxkhKg5XuO4DjJAZPQQWuZ8CjvM95MNjDNZz5fOEoENHubUrlc7mk&_nc_ohc=bRvo0M-7NjcQ7kNvwFG2pu6&_nc_gid=tQdSKa33rVmLjaXNzJWzRQ&edm=ANTKIIoBAAAA&ccb=7-5&oh=00_AfbuF6UwMXp2JASNrjzpC4F528XgQzav5EZE2zpusDpMqg&oe=68E0AD20&_nc_sid=d885a2",
            "username": "vladislavlev.i"
        },
        "likes_count": 0,
        "answers": []
    },
    {
        "id": "17870606248036421",
        "created_at": 1484822311,
        "text": "\u0421\u043a\u0430\u0437\u043e\u0447\u043d\u0430\u044f \u0440\u0430\u0431\u043e\u0442\u0430! \u043f\u043e \u043c\u043e\u0442\u0438\u0432\u0430\u043c \u0440\u0443\u0441\u0441\u043a\u043e\u0439 \u043d\u0430\u0440\u043e\u0434\u043d\u043e\u0439 \u0441\u043a\u0430\u0437\u043a\u0438 \"\u041d\u043e\u0432\u044b\u0439 NewBalance 1 \u0421\u0435\u043a\u0440\u0435\u0442\u0430\u0440\u044f\"",
        "owner": {
            "id": "13821",
            "is_verified": false,
            "profile_pic_url": "https://instagram.ftlv27-1.fna.fbcdn.net/v/t51.2885-19/465852166_1254231312435243_2004485542291215777_n.jpg?stp=dst-jpg_s150x150_tt6&efg=eyJ2ZW5jb2RlX3RhZyI6InByb2ZpbGVfcGljLmRqYW5nby42ODEuYzIifQ&_nc_ht=instagram.ftlv27-1.fna.fbcdn.net&_nc_cat=103&_nc_oc=Q6cZ2QHfvPinENG-UXbxkhKg5XuO4DjJAZPQQWuZ8CjvM95MNjDNZz5fOEoENHubUrlc7mk&_nc_ohc=P_Tq-SKQ99QQ7kNvwGLlwX-&_nc_gid=tQdSKa33rVmLjaXNzJWzRQ&edm=ANTKIIoBAAAA&ccb=7-5&oh=00_AfayWW8TT1e2T7rNkndVlXia3Ivxa0Pct6ZnCqfYB81G_g&oe=68E09724&_nc_sid=d885a2",
            "username": "foxtrotru"
        },
        "likes_count": 2,
        "answers": []
    },
    {
        "id": "17863730761067122",
        "created_at": 1484816102,
        "text": "Awesome!",
        "owner": {
            "id": "4236212555",
            "is_verified": false,
            "profile_pic_url": "https://instagram.ftlv27-1.fna.fbcdn.net/v/t51.2885-19/14712242_1640052912962092_1776556275019022336_a.jpg?stp=dst-jpg_s150x150_tt6&efg=eyJ2ZW5jb2RlX3RhZyI6InByb2ZpbGVfcGljLmRqYW5nby4xMDgwLmMyIn0&_nc_ht=instagram.ftlv27-1.fna.fbcdn.net&_nc_cat=104&_nc_oc=Q6cZ2QHfvPinENG-UXbxkhKg5XuO4DjJAZPQQWuZ8CjvM95MNjDNZz5fOEoENHubUrlc7mk&_nc_ohc=t67hD0Kj9AwQ7kNvwGCqm2E&_nc_gid=tQdSKa33rVmLjaXNzJWzRQ&edm=ANTKIIoBAAAA&ccb=7-5&oh=00_Afb7O5e7pJh8ukyjW45rTf5PCgRRngkvkM133OcV0pmxYQ&oe=68E0C8CB&_nc_sid=d885a2",
            "username": "swaggaink"
        },
        "likes_count": 0,
        "answers": []
    },
    {
        "id": "17857848073092046",
        "created_at": 1484814248,
        "text": "Nice!",
        "owner": {
            "id": "21513591",
            "is_verified": false,
            "profile_pic_url": "https://instagram.fsdv1-2.fna.fbcdn.net/v/t51.2885-19/271216505_289244319912962_6613477926464325471_n.jpg?stp=dst-jpg_s150x150_tt6&efg=eyJ2ZW5jb2RlX3RhZyI6InByb2ZpbGVfcGljLmRqYW5nby4xMDgwLmMyIn0&_nc_ht=instagram.fsdv1-2.fna.fbcdn.net&_nc_cat=102&_nc_oc=Q6cZ2QHfvPinENG-UXbxkhKg5XuO4DjJAZPQQWuZ8CjvM95MNjDNZz5fOEoENHubUrlc7mk&_nc_ohc=70spLdCS948Q7kNvwF1hfuN&_nc_gid=tQdSKa33rVmLjaXNzJWzRQ&edm=ANTKIIoBAAAA&ccb=7-5&oh=00_AfYxbP2IjfnMZJOfNh9AmkdlFAocMXl9KtmYLbDjLOmrvA&oe=68E09204&_nc_sid=d885a2",
            "username": "kingbex"
        },
        "likes_count": 0,
        "answers": []
    },
    {
        "id": "17861220568073218",
        "created_at": 1484814119,
        "text": "\u0420\u043e\u0441\u043a\u043e\u0448\u043d\u043e!",
        "owner": {
            "id": "9788239",
            "is_verified": false,
            "profile_pic_url": "https://instagram.ftlv27-1.fna.fbcdn.net/v/t51.2885-19/521364013_18513857422060240_4908863477437248431_n.jpg?stp=dst-jpg_s150x150_tt6&efg=eyJ2ZW5jb2RlX3RhZyI6InByb2ZpbGVfcGljLmRqYW5nby4xMDgwLmMyIn0&_nc_ht=instagram.ftlv27-1.fna.fbcdn.net&_nc_cat=104&_nc_oc=Q6cZ2QHfvPinENG-UXbxkhKg5XuO4DjJAZPQQWuZ8CjvM95MNjDNZz5fOEoENHubUrlc7mk&_nc_ohc=Zt-jAR16qqcQ7kNvwGhkK-g&_nc_gid=tQdSKa33rVmLjaXNzJWzRQ&edm=ANTKIIoBAAAA&ccb=7-5&oh=00_Afa4GECPdk4_z5uhGSrWKH4wLx7qbiLX96KPZHBSPQXYbQ&oe=68E0AA6E&_nc_sid=d885a2",
            "username": "autograff"
        },
        "likes_count": 0,
        "answers": []
    },
    {
        "id": "17857755256088603",
        "created_at": 1484812626,
        "text": "\ud83d\udc4f\ud83c\udffb\ud83d\udc4f\ud83c\udffb\ud83d\udc4f\ud83c\udffb",
        "owner": {
            "id": "544703381",
            "is_verified": false,
            "profile_pic_url": "https://instagram.ftlv27-1.fna.fbcdn.net/v/t51.2885-19/334446831_238081215225608_4062918666606683234_n.jpg?stp=dst-jpg_s150x150_tt6&efg=eyJ2ZW5jb2RlX3RhZyI6InByb2ZpbGVfcGljLmRqYW5nby4xMDgwLmMyIn0&_nc_ht=instagram.ftlv27-1.fna.fbcdn.net&_nc_cat=108&_nc_oc=Q6cZ2QHfvPinENG-UXbxkhKg5XuO4DjJAZPQQWuZ8CjvM95MNjDNZz5fOEoENHubUrlc7mk&_nc_ohc=80qBbB9luuAQ7kNvwE_GlHN&_nc_gid=tQdSKa33rVmLjaXNzJWzRQ&edm=ANTKIIoBAAAA&ccb=7-5&oh=00_AfbgLxdh6KqthGiCX-nyVHIOGu1Ws6uNUhqKoXNkS31SUA&oe=68E0C4B9&_nc_sid=d885a2",
            "username": "vitaliy_house"
        },
        "likes_count": 0,
        "answers": []
    },
    {
        "id": "17870931871038449",
        "created_at": 1484812380,
        "text": "\ud83d\udc4f\ud83d\udc4f\ud83d\udc4f\ud83d\udc4d",
        "owner": {
            "id": "50440150",
            "is_verified": false,
            "profile_pic_url": "https://instagram.ftlv27-1.fna.fbcdn.net/v/t51.2885-19/11326154_125739074435864_808088756_a.jpg?stp=dst-jpg_s150x150_tt6&efg=eyJ2ZW5jb2RlX3RhZyI6InByb2ZpbGVfcGljLmRqYW5nby4xNTAuYzIifQ&_nc_ht=instagram.ftlv27-1.fna.fbcdn.net&_nc_cat=108&_nc_oc=Q6cZ2QHfvPinENG-UXbxkhKg5XuO4DjJAZPQQWuZ8CjvM95MNjDNZz5fOEoENHubUrlc7mk&_nc_ohc=Ry1f1xcQZ64Q7kNvwEfMOph&_nc_gid=tQdSKa33rVmLjaXNzJWzRQ&edm=ANTKIIoBAAAA&ccb=7-5&oh=00_AfZzV2uIDza41MgGeIysGA1JEGtVKy_snUd6TzCTe830Yg&oe=68E0A043&_nc_sid=d885a2",
            "username": "thedrserge"
        },
        "likes_count": 0,
        "answers": []
    },
    {
        "id": "17859083053129509",
        "created_at": 1484811951,
        "text": "@sb210979 \ud83d\udc4c",
        "owner": {
            "id": "1921708512",
            "is_verified": false,
            "profile_pic_url": "https://instagram.ftlv27-1.fna.fbcdn.net/v/t51.2885-19/59335079_2025085557600952_997056982521217024_n.jpg?stp=dst-jpg_s150x150_tt6&efg=eyJ2ZW5jb2RlX3RhZyI6InByb2ZpbGVfcGljLmRqYW5nby4xMDgwLmMyIn0&_nc_ht=instagram.ftlv27-1.fna.fbcdn.net&_nc_cat=104&_nc_oc=Q6cZ2QHfvPinENG-UXbxkhKg5XuO4DjJAZPQQWuZ8CjvM95MNjDNZz5fOEoENHubUrlc7mk&_nc_ohc=xfIuUQdy_74Q7kNvwEaVkaF&_nc_gid=tQdSKa33rVmLjaXNzJWzRQ&edm=ANTKIIoBAAAA&ccb=7-5&oh=00_AfanZorbQ_cuKLcU3cANY2sWvbOeThFE3I7PhM9TMlqh6Q&oe=68E0BBB3&_nc_sid=d885a2",
            "username": "zoomstreetart"
        },
        "likes_count": 0,
        "answers": []
    },
    {
        "id": "17847323863182017",
        "created_at": 1484811524,
        "text": "\u041f\u0440\u0435\u043a\u0440\u0430\u0441\u043d\u043e! \ud83d\ude4c\ud83c\udffb",
        "owner": {
            "id": "1888112",
            "is_verified": false,
            "profile_pic_url": "https://instagram.ftlv18-1.fna.fbcdn.net/v/t51.2885-19/451385264_1023721235768755_2951305195966158744_n.jpg?stp=dst-jpg_s150x150_tt6&efg=eyJ2ZW5jb2RlX3RhZyI6InByb2ZpbGVfcGljLmRqYW5nby4xMDgwLmMyIn0&_nc_ht=instagram.ftlv18-1.fna.fbcdn.net&_nc_cat=107&_nc_oc=Q6cZ2QHfvPinENG-UXbxkhKg5XuO4DjJAZPQQWuZ8CjvM95MNjDNZz5fOEoENHubUrlc7mk&_nc_ohc=wAJP1FWm31UQ7kNvwHWczIL&_nc_gid=tQdSKa33rVmLjaXNzJWzRQ&edm=ANTKIIoBAAAA&ccb=7-5&oh=00_AfYh8FuwCXSYWzxRre4jcCeL0Ko1itJjI_-IrFyi3Kk0WQ&oe=68E0B5A9&_nc_sid=d885a2",
            "username": "julie.krutikova"
        },
        "likes_count": 0,
        "answers": []
    },
    {
        "id": "17864735419066305",
        "created_at": 1484811365,
        "text": "@zoomstreetart \u0437\u0430\u0447\u0451\u0442 ))) \u0443\u0434\u0430\u0440\u0438\u043c \ud83c\udf3d\u043f\u043e \u0446\u0435\u043b\u0438\u043d\u0435 \ud83d\ude9c",
        "owner": {
            "id": "2953666989",
            "is_verified": false,
            "profile_pic_url": "https://instagram.fsdv1-2.fna.fbcdn.net/v/t51.2885-19/437361485_809988541017890_5355025336374245601_n.jpg?stp=dst-jpg_s150x150_tt6&efg=eyJ2ZW5jb2RlX3RhZyI6InByb2ZpbGVfcGljLmRqYW5nby4xMDgwLmMyIn0&_nc_ht=instagram.fsdv1-2.fna.fbcdn.net&_nc_cat=102&_nc_oc=Q6cZ2QHfvPinENG-UXbxkhKg5XuO4DjJAZPQQWuZ8CjvM95MNjDNZz5fOEoENHubUrlc7mk&_nc_ohc=GjiQd2W8YHAQ7kNvwGLT3zI&_nc_gid=tQdSKa33rVmLjaXNzJWzRQ&edm=ANTKIIoBAAAA&ccb=7-5&oh=00_AfYMswYf1bWk4slrtSmfBVfLRnnB855TPpV10xXv1jCPxg&oe=68E0C54F&_nc_sid=d885a2",
            "username": "sb210979"
        },
        "likes_count": 1,
        "answers": []
    },
    {
        "id": "17857797691082843",
        "created_at": 1484811202,
        "text": "#streetart #moscowstreetart #streetartist #sprayart #stencilart #russia #moscow #mural #art #urbanart #undergroundart #artwork #graffiti #stencil #zoomstreetart #zoom #\u0441\u0442\u0440\u0438\u0442\u0430\u0440\u0442 #street_art #\u0433\u0440\u0430\u0444\u0444\u0438\u0442\u0438 #urban #urbanwalls #\u043c\u043e\u0441\u043a\u0432\u0430 #\u0437\u0443\u043c #dirtyart #\u0425\u0440\u0443\u0449\u0435\u0432 #\u041e\u041e\u041d #Khrushchev #UN #\u041a\u0430\u0440\u0438\u0431\u0441\u043a\u0438\u0439\u041a\u0440\u0438\u0437\u0438\u0441",
        "owner": {
            "id": "1921708512",
            "is_verified": false,
            "profile_pic_url": "https://instagram.ftlv27-1.fna.fbcdn.net/v/t51.2885-19/59335079_2025085557600952_997056982521217024_n.jpg?stp=dst-jpg_s150x150_tt6&efg=eyJ2ZW5jb2RlX3RhZyI6InByb2ZpbGVfcGljLmRqYW5nby4xMDgwLmMyIn0&_nc_ht=instagram.ftlv27-1.fna.fbcdn.net&_nc_cat=104&_nc_oc=Q6cZ2QHfvPinENG-UXbxkhKg5XuO4DjJAZPQQWuZ8CjvM95MNjDNZz5fOEoENHubUrlc7mk&_nc_ohc=xfIuUQdy_74Q7kNvwEaVkaF&_nc_gid=tQdSKa33rVmLjaXNzJWzRQ&edm=ANTKIIoBAAAA&ccb=7-5&oh=00_AfanZorbQ_cuKLcU3cANY2sWvbOeThFE3I7PhM9TMlqh6Q&oe=68E0BBB3&_nc_sid=d885a2",
            "username": "zoomstreetart"
        },
        "likes_count": 0,
        "answers": []
    }
]